abtranslate/__init__.py
abtranslate/main.py
abtranslate/config/__init__.py
abtranslate/config/constants.py
abtranslate/config/settings.py
abtranslate/config/translator.py
abtranslate/translation/preprocessing.py
abtranslate/translation/spark_translation.py
abtranslate/translator/__init__.py
abtranslate/translator/apply_bpe.py
abtranslate/translator/argos_translator.py
abtranslate/translator/custom_translator.py
abtranslate/translator/marian_translator.py
abtranslate/translator/package.py
abtranslate/translator/sentencizer.py
abtranslate/translator/tokenizer.py
abtranslate/translator/translator_interface.py
abtranslate/utils/exception.py
abtranslate/utils/file_manager.py
abtranslate/utils/helper.py
abtranslate/utils/logger.py
abtranslate/utils/validator.py
abtranslate-0.2.0.dist-info/licenses/LICENSE
abtranslate-0.2.0.dist-info/METADATA
abtranslate-0.2.0.dist-info/WHEEL
abtranslate-0.2.0.dist-info/entry_points.txt
abtranslate-0.2.0.dist-info/top_level.txt
abtranslate-0.2.0.dist-info/RECORD
