Metadata-Version: 2.4
Name: abtranslate
Version: 0.2.0
Summary: A translator wrapper for open-source translation models with batch optimization. Currently supports ArgosTranslate models and is designed for scalable deployment.
Home-page: https://github.com/ichsan-t45/abtranslate
Author: Ichsan Takwa
Author-email: ichsantakwa <ichsantakwa@gmail.com>
Requires-Python: >=3.10
License-File: LICENSE
Requires-Dist: ctranslate2>=3.17.0
Requires-Dist: pandas>=2.3.0
Requires-Dist: pytest>=8.4.1
Requires-Dist: sentencepiece>=0.2.0
Requires-Dist: stanza==1.1.1
Requires-Dist: regex>=2024.11.6
Requires-Dist: build>=1.3.0
Dynamic: license-file
